shadowproxy/__init__.py
shadowproxy/__main__.py
shadowproxy/ciphers.py
shadowproxy/gvars.py
shadowproxy/utils.py
shadowproxy/plugins/__init__.py
shadowproxy/plugins/base.py
shadowproxy/plugins/http_simple.py
shadowproxy/plugins/tls1_2.py
shadowproxy/plugins/tls_parser.py
shadowproxy/protocols/__init__.py
shadowproxy/protocols/exceptions.py
shadowproxy/protocols/http.py
shadowproxy/protocols/socks4.py
shadowproxy/protocols/socks5.py
shadowproxy/proxies/__init__.py
shadowproxy/proxies/aead/__init__.py
shadowproxy/proxies/aead/client.py
shadowproxy/proxies/aead/parser.py
shadowproxy/proxies/aead/server.py
shadowproxy/proxies/base/__init__.py
shadowproxy/proxies/base/client.py
shadowproxy/proxies/base/server.py
shadowproxy/proxies/base/udpclient.py
shadowproxy/proxies/base/udpserver.py
shadowproxy/proxies/http/__init__.py
shadowproxy/proxies/http/client.py
shadowproxy/proxies/http/server.py
shadowproxy/proxies/shadowsocks/__init__.py
shadowproxy/proxies/shadowsocks/client.py
shadowproxy/proxies/shadowsocks/parser.py
shadowproxy/proxies/shadowsocks/server.py
shadowproxy/proxies/shadowsocks/udpclient.py
shadowproxy/proxies/shadowsocks/udpserver.py
shadowproxy/proxies/socks/__init__.py
shadowproxy/proxies/socks/client.py
shadowproxy/proxies/socks/server.py
shadowproxy/proxies/transparent/__init__.py
shadowproxy/proxies/transparent/server.py
shadowproxy/proxies/transparent/udpserver.py
shadowproxy/proxies/tunnel/__init__.py
shadowproxy/proxies/tunnel/udpserver.py
shadowproxy-0.7.0.dist-info/LICENSE
shadowproxy-0.7.0.dist-info/METADATA
shadowproxy-0.7.0.dist-info/WHEEL
shadowproxy-0.7.0.dist-info/entry_points.txt
shadowproxy-0.7.0.dist-info/top_level.txt
shadowproxy-0.7.0.dist-info/RECORD
