Metadata-Version: 2.1
Name: shadowproxy
Version: 0.7.0
Summary: A proxy server that implements Socks5/Shadowsocks/Redirect/HTTP (tcp) and Shadowsocks/TProxy/Tunnel (udp) protocols.
Home-page: https://github.com/guyingbo/shadowproxy
Author: Yingbo Gu
Author-email: tensiongyb@gmail.com
Maintainer: Yingbo Gu
Maintainer-email: tensiongyb@gmail.com
License: MIT
Platform: UNKNOWN
Classifier: License :: OSI Approved :: MIT License
Classifier: Programming Language :: Python :: 3.6
Classifier: Programming Language :: Python :: 3.7
Classifier: Programming Language :: Python :: 3.8
Requires-Dist: pycryptodome (>=3.4.3)
Requires-Dist: curio (==0.9)
Requires-Dist: pylru (>=1.0.9)
Requires-Dist: iofree (>=0.2.4)
Requires-Dist: httptools
Requires-Dist: hkdf
